semantic_pydantic/version.py
semantic_pydantic/__init__.py
semantic_pydantic/api.py
semantic_pydantic/py.typed
semantic_pydantic-0.0.4.dist-info/licenses/LICENSE
semantic_pydantic-0.0.4.dist-info/WHEEL
semantic_pydantic-0.0.4.dist-info/METADATA
semantic_pydantic-0.0.4.dist-info/RECORD
