Metadata-Version: 2.4
Name: semantic-pydantic
Version: 0.0.4
Summary: Integration between the Bioregistry and Pydantic type annotations.
Keywords: snekpack,cookiecutter,pydantic,bioregistry,fastapi
Author: Charles Tapley Hoyt
Author-email: Charles Tapley Hoyt <cthoyt@gmail.com>
License-File: LICENSE
Classifier: Development Status :: 1 - Planning
Classifier: Environment :: Console
Classifier: Intended Audience :: Developers
Classifier: License :: OSI Approved :: MIT License
Classifier: Operating System :: OS Independent
Classifier: Framework :: Pytest
Classifier: Framework :: tox
Classifier: Framework :: Sphinx
Classifier: Natural Language :: English
Classifier: Programming Language :: Python
Classifier: Programming Language :: Python :: 3.10
Classifier: Programming Language :: Python :: 3.11
Classifier: Programming Language :: Python :: 3.12
Classifier: Programming Language :: Python :: 3.13
Classifier: Programming Language :: Python :: 3 :: Only
Classifier: Typing :: Typed
Classifier: Framework :: Pydantic
Classifier: Framework :: Pydantic :: 2
Classifier: Framework :: FastAPI
Requires-Dist: bioregistry
Requires-Dist: requests
Requires-Dist: pydantic>=2.0
Maintainer: Charles Tapley Hoyt
Maintainer-email: Charles Tapley Hoyt <cthoyt@gmail.com>
Requires-Python: >=3.10
Project-URL: Bug Tracker, https://github.com/cthoyt/semantic-pydantic/issues
Project-URL: Documentation, https://semantic-pydantic.readthedocs.io
Project-URL: Funding, https://github.com/sponsors/cthoyt
Project-URL: Homepage, https://github.com/cthoyt/semantic-pydantic
Project-URL: Repository, https://github.com/cthoyt/semantic-pydantic.git
Provides-Extra: docs
Provides-Extra: fastapi
Provides-Extra: tests
